ovos_google_translate_plugin/__init__.py
ovos_google_translate_plugin/version.py
ovos_google_translate_plugin-0.0.3a2.dist-info/LICENSE
ovos_google_translate_plugin-0.0.3a2.dist-info/METADATA
ovos_google_translate_plugin-0.0.3a2.dist-info/WHEEL
ovos_google_translate_plugin-0.0.3a2.dist-info/entry_points.txt
ovos_google_translate_plugin-0.0.3a2.dist-info/top_level.txt
ovos_google_translate_plugin-0.0.3a2.dist-info/RECORD
