Metadata-Version: 2.1
Name: ovos-google-translate-plugin
Version: 0.0.3a2
Summary: OVOS translation module for google
Home-page: https://github.com/OpenVoiceOS/ovos-google-translate-plugin
Author: jarbasAi
Author-email: jarbasai@mailfence.com
License: Apache-2.0
Platform: UNKNOWN
Classifier: Intended Audience :: Developers
Classifier: Topic :: Text Processing :: Linguistic
Classifier: License :: OSI Approved :: Apache Software License
Classifier: Programming Language :: Python :: 3.6
Classifier: Programming Language :: Python :: 3.7
Classifier: Programming Language :: Python :: 3.8
Classifier: Programming Language :: Python :: 3.9
Classifier: Programming Language :: Python :: 3.10
Classifier: Programming Language :: Python :: 3.11
Requires-Dist: requests
Requires-Dist: ovos-plugin-manager<2.0.0,>=1.0.0
